Opsy-0.3.0.data/data/etc/opsy/opsy.toml.example
opsy/__init__.py
opsy/app.py
opsy/config.py
opsy/exceptions.py
opsy/flask_extensions.py
opsy/logging.py
opsy/models.py
opsy/rbac.py
opsy/schema.py
opsy/server.py
opsy/shell.py
opsy/utils.py
opsy/auth/__init__.py
opsy/auth/models.py
opsy/auth/schema.py
opsy/auth/utils.py
opsy/auth/views.py
opsy/inventory/__init__.py
opsy/inventory/models.py
opsy/inventory/schema.py
opsy/inventory/views.py
opsy/monitoring/__init__.py
opsy/monitoring/exceptions.py
opsy/monitoring/models.py
opsy/monitoring/routes.py
opsy/monitoring/schema.py
opsy/monitoring/views.py
opsy/monitoring/backends/__init__.py
opsy/monitoring/backends/base.py
opsy/monitoring/backends/sensu.py
opsy/static/.gitkeep
Opsy-0.3.0.dist-info/LICENSE
Opsy-0.3.0.dist-info/METADATA
Opsy-0.3.0.dist-info/WHEEL
Opsy-0.3.0.dist-info/entry_points.txt
Opsy-0.3.0.dist-info/pbr.json
Opsy-0.3.0.dist-info/top_level.txt
Opsy-0.3.0.dist-info/RECORD
