Metadata-Version: 2.1
Name: Opsy
Version: 0.3.0
Summary: A multi-user/role inventory system
Home-page: https://github.com/testeddoughnut/opsy
Author: Opsy
License: MIT
Platform: UNKNOWN
Classifier: Development Status :: 3 - Alpha
Classifier: Environment :: Web Environment
Classifier: Framework :: Flask
Classifier: Intended Audience :: System Administrators
Classifier: License :: OSI Approved :: MIT License
Classifier: Operating System :: POSIX :: Linux
Classifier: Programming Language :: Python :: 3.6
Classifier: Programming Language :: Python :: 3.7
Classifier: Programming Language :: Python :: 3.8
Classifier: Programming Language :: Python :: 3 :: Only
Classifier: Topic :: System :: Systems Administration
Requires-Dist: aiohttp (==3.5.1)
Requires-Dist: apispec (==2.0.2)
Requires-Dist: cheroot (==8.0.0)
Requires-Dist: Flask (==1.1.1)
Requires-Dist: flask-allows (==0.7.1)
Requires-Dist: flask-apispec (==0.8.4)
Requires-Dist: Flask-JSGlue (==0.3.1)
Requires-Dist: flask-ldap3-login (==0.9.16)
Requires-Dist: Flask-Login (==0.4.1)
Requires-Dist: flask-marshmallow (==0.10.1)
Requires-Dist: Flask-Migrate (==2.5.2)
Requires-Dist: Flask-SQLAlchemy (==2.4.0)
Requires-Dist: marshmallow (==3.2.1)
Requires-Dist: marshmallow-sqlalchemy (==0.17.0)
Requires-Dist: pbr (==5.1.1)
Requires-Dist: prometheus-flask-exporter (==0.12.1)
Requires-Dist: psycopg2-binary (==2.8.2)
Requires-Dist: pyOpenSSL (==19.0.0)
Requires-Dist: python-dateutil (==2.7.5)
Requires-Dist: stevedore (==1.30.0)
Requires-Dist: toml (==0.10.0)
Requires-Dist: webargs (==5.3.2)
Provides-Extra: test
Requires-Dist: coverage (==4.5.4) ; extra == 'test'
Requires-Dist: Faker (==2.0.0) ; extra == 'test'
Requires-Dist: pycodestyle (==2.4.0) ; extra == 'test'
Requires-Dist: pydocstyle (==3.0.0) ; extra == 'test'
Requires-Dist: pylint (==2.3.0) ; extra == 'test'
Requires-Dist: pylint-flask (==0.6) ; extra == 'test'
Requires-Dist: pytest (==5.0.1) ; extra == 'test'
Requires-Dist: pytest-cov (==2.7.1) ; extra == 'test'
Requires-Dist: pytest-flask (==0.15.0) ; extra == 'test'
Requires-Dist: pytest-flask-sqlalchemy (==1.0.2) ; extra == 'test'
Requires-Dist: pytest-mock (==1.11.0) ; extra == 'test'
Requires-Dist: requests (==2.22.0) ; extra == 'test'
Requires-Dist: tox (==3.13.2) ; extra == 'test'
